twisted_fate/__init__.py
twisted_fate/api_wrapper/__init__.py
twisted_fate/api_wrapper/active_game.py
twisted_fate/api_wrapper/card.py
twisted_fate/api_wrapper/client_api.py
twisted_fate/api_wrapper/deck.py
twisted_fate/api_wrapper/utils.py
twisted_fate/data/data/globals-en_us.json
twisted_fate/data/data/set1-en_us.json
twisted_fate/data/data/set2-en_us.json
twisted_fate/data/data/set3-en_us.json
twisted_fate/deck_coder/__init__.py
twisted_fate/deck_coder/deckCoder.py
twisted_fate-0.1.5.dist-info/LICENSE
twisted_fate-0.1.5.dist-info/WHEEL
twisted_fate-0.1.5.dist-info/METADATA
twisted_fate-0.1.5.dist-info/RECORD
