Metadata-Version: 2.1
Name: twisted-fate
Version: 0.1.5
Summary: An api wrapper around the Legends of Runeterra Client API with deck encoder implementation
Home-page: https://github.com/Snowcola/twisted_fate
License: MIT
Author: Anthony Keelan
Author-email: anthony.keelan@gmail.com
Requires-Python: >=3.6,<4.0
Classifier: Intended Audience :: Developers
Classifier: License :: OSI Approved :: MIT License
Classifier: Operating System :: OS Independent
Classifier: Programming Language :: Python :: 3
Classifier: Programming Language :: Python :: 3.6
Classifier: Programming Language :: Python :: 3.7
Classifier: Programming Language :: Python :: 3.8
Classifier: Programming Language :: Python :: 3.9
Requires-Dist: requests (>=2.22,<3.0)
Project-URL: Repository, https://github.com/Snowcola/twisted_fate
